{
 "traps": {
  "spike": [
   {
    "art": "spike",
    "fx": 0.501,
    "fy": 6,
    "h": 70
   }
  ],
  "flame": [
   {
    "art": "flame",
    "fx": 0.303,
    "fy": 14,
    "h": 130
   }
  ],
  "venom": [
   {
    "art": "poison1",
    "fx": 0.321,
    "fy": 25,
    "h": 75
   },
   {
    "art": "poison2",
    "fx": 0.688,
    "fy": 18,
    "h": 68
   }
  ]
 },
 "candles": [
  {
   "art": "candle",
   "fx": 0.154,
   "fy": 120,
   "h": 26
  },
  {
   "art": "candle",
   "fx": 0.856,
   "fy": 121,
   "h": 26
  }
 ]
}